<?xml version="1.0" encoding="utf-8" ?><dwsync><file name="home.php" server="Macintosh HD/Applications/XAMPP/xamppfiles/htdocs/" local="3528977061" remote="1100394710940773029" Dst="-1" /><file name="header.php" server="Macintosh HD/Applications/XAMPP/xamppfiles/htdocs/" local="3524042544" remote="7819009840" Dst="-1" /><file name="footer.php" server="Macintosh HD/Applications/XAMPP/xamppfiles/htdocs/" local="3527824484" remote="-8749676963514919836" Dst="-1" /><file name="footer.php" server="sukhakartahospital.com" local="3510208685" remote="7805130976" Dst="-1" /><file name="header.php" server="sukhakartahospital.com" local="3510755506" remote="7805677756" Dst="-1" /><file name="home.php" server="sukhakartahospital.com" local="3510205325" remote="12100097492" Dst="-1" /><file name="home.php" server="109.73.234.188/meraki/" local="3522062443" remote="4454373292726147580" Dst="-1" /><file name="home.php" server="178.62.65.198/../../var/www/" local="3522984343" remote="7817951642" Dst="-1" /><file name="header.php" server="178.62.65.198/../../var/www/" local="3522896918" remote="2942325245806846998" Dst="-1" /><file name="home.php" server="178.62.65.198/../../var/www/merakijewel.com/public_html/" local="3531416944" remote="7826384240" Dst="-1" /><file name="footer.php" server="178.62.65.198/../../var/www/merakijewel.com/public_html/" local="3527824484" remote="-8942066931163700038" Dst="-1" /><file name="header.php" server="178.62.65.198/../../var/www/merakijewel.com/public_html/" local="3528179754" remote="7823147051" Dst="-1" /></dwsync>